stone_in_waiting/__init__.py
stone_in_waiting/stone_in_waiting.py
stone_in_waiting-0.0.1.dist-info/LICENSE
stone_in_waiting-0.0.1.dist-info/METADATA
stone_in_waiting-0.0.1.dist-info/WHEEL
stone_in_waiting-0.0.1.dist-info/top_level.txt
stone_in_waiting-0.0.1.dist-info/RECORD
